README.md
setup.py
bankrupt/__init__.py
bankrupt/allocators.py
bankrupt.egg-info/PKG-INFO
bankrupt.egg-info/SOURCES.txt
bankrupt.egg-info/dependency_links.txt
bankrupt.egg-info/not-zip-safe
bankrupt.egg-info/top_level.txt