Metadata-Version: 1.1
Name: bankrupt
Version: 0.2.1
Summary: Allocator of the bankruptcy problem.
Home-page: https://github.com/xianqiu/Bankrupt
Author: qx3501332
Author-email: x.qiu@qq.com
License: MIT License
Platform: UNKNOWN
Classifier: Development Status :: 4 - Beta
Classifier: Intended Audience :: Developers
Classifier: Operating System :: OS Independent
Classifier: Programming Language :: Python :: 3.6
Classifier: Topic :: Software Development :: Libraries :: Python Modules
